README.md
setup.cfg
setup.py
blueflood_graphite_finder/__init__.py
blueflood_graphite_finder/auth.py
blueflood_graphite_finder/blueflood.py
blueflood_graphite_finder/rax_auth.py
blueflood_graphite_finder.egg-info/PKG-INFO
blueflood_graphite_finder.egg-info/SOURCES.txt
blueflood_graphite_finder.egg-info/dependency_links.txt
blueflood_graphite_finder.egg-info/not-zip-safe
blueflood_graphite_finder.egg-info/requires.txt
blueflood_graphite_finder.egg-info/top_level.txt