Metadata-Version: 1.1
Name: blueflood-graphite-finder
Version: 1.1.4
Summary: A plugin for using graphite-web and graphite-api with Blueflood
Home-page: https://github.com/rackerlabs/blueflood-graphite-finder
Author: Rackspace Metrics
Author-email: cloudMetrics-dev@lists.rackspace.com
License: Apache Software License 2.0
Keywords: blueflood graphite finder metrics
Platform: any
Classifier: Intended Audience :: Developers
Classifier: Intended Audience :: System Administrators
Classifier: License :: OSI Approved :: BSD License
Classifier: Operating System :: OS Independent
Classifier: Programming Language :: Python
Classifier: Programming Language :: Python :: 2
Classifier: Topic :: System :: Monitoring
